albucore/__init__.py
albucore/decorators.py
albucore/functions.py
albucore/utils.py
albumentations/__init__.py
albumentations/augmentations/__init__.py
albumentations/augmentations/blur/__init__.py
albumentations/augmentations/blur/functional.py
albumentations/augmentations/blur/transforms.py
albumentations/augmentations/crops/__init__.py
albumentations/augmentations/crops/functional.py
albumentations/augmentations/crops/transforms.py
albumentations/augmentations/dropout/__init__.py
albumentations/augmentations/dropout/channel_dropout.py
albumentations/augmentations/dropout/coarse_dropout.py
albumentations/augmentations/dropout/functional.py
albumentations/augmentations/dropout/grid_dropout.py
albumentations/augmentations/dropout/mask_dropout.py
albumentations/augmentations/dropout/transforms.py
albumentations/augmentations/dropout/xy_masking.py
albumentations/augmentations/geometric/__init__.py
albumentations/augmentations/geometric/distortion.py
albumentations/augmentations/geometric/flip.py
albumentations/augmentations/geometric/functional.py
albumentations/augmentations/geometric/pad.py
albumentations/augmentations/geometric/resize.py
albumentations/augmentations/geometric/rotate.py
albumentations/augmentations/geometric/transforms.py
albumentations/augmentations/mixing/__init__.py
albumentations/augmentations/mixing/domain_adaptation.py
albumentations/augmentations/mixing/domain_adaptation_functional.py
albumentations/augmentations/mixing/functional.py
albumentations/augmentations/mixing/transforms.py
albumentations/augmentations/other/__init__.py
albumentations/augmentations/other/lambda_transform.py
albumentations/augmentations/other/type_transform.py
albumentations/augmentations/pixel/__init__.py
albumentations/augmentations/pixel/functional.py
albumentations/augmentations/pixel/transforms.py
albumentations/augmentations/spectrogram/__init__.py
albumentations/augmentations/spectrogram/transform.py
albumentations/augmentations/text/__init__.py
nrtk_albumentations-2.2.1.dist-info/METADATA
nrtk_albumentations-2.2.1.dist-info/WHEEL
nrtk_albumentations-2.2.1.dist-info/licenses/LICENSE
nrtk_albumentations-2.2.1.dist-info/RECORD
