Metadata-Version: 2.4
Name: nrtk-albumentations
Version: 2.2.1
Summary: Fork of Albumentations in direct support of NRTK (Natural Robustness Toolkit). Fast, flexible, and advanced augmentation library for deep learning, computer vision, and medical imaging. Offers a wide range of transformations for both 2D (images, masks, bboxes, keypoints) and 3D (volumes, volumetric masks, keypoints) data, with optimized performance and seamless integration into ML workflows.
License: MIT
License-File: LICENSE
Keywords: 2D augmentation,3D augmentation,aerial photography,anomaly detection,artificial intelligence,autonomous driving,bounding boxes,classification,computer vision,computer vision library,data augmentation,data preprocessing,data science,deep learning,deep learning library,depth estimation,face recognition,fast augmentation,image augmentation,image processing,image transformation,images,instance segmentation,keras,keypoint detection,keypoints,machine learning,machine learning tools,masks,med
Author: Vladimir Iglovikov
Maintainer: Kitware, Inc.
Maintainer-email: nrtk@kitware.com
Requires-Python: >=3.10,<4.0
Classifier: Development Status :: 5 - Production/Stable
Classifier: Intended Audience :: Developers
Classifier: Intended Audience :: Healthcare Industry
Classifier: Intended Audience :: Information Technology
Classifier: Intended Audience :: Science/Research
Classifier: License :: OSI Approved :: MIT License
Classifier: Operating System :: OS Independent
Classifier: Programming Language :: Python
Classifier: Programming Language :: Python :: 3
Classifier: Programming Language :: Python :: 3.10
Classifier: Programming Language :: Python :: 3.11
Classifier: Programming Language :: Python :: 3.12
Classifier: Programming Language :: Python :: 3.13
Classifier: Programming Language :: Python :: 3.14
Classifier: Programming Language :: Python :: 3 :: Only
Classifier: Topic :: Scientific/Engineering
Classifier: Topic :: Scientific/Engineering :: Artificial Intelligence
Classifier: Topic :: Scientific/Engineering :: Astronomy
Classifier: Topic :: Scientific/Engineering :: Atmospheric Science
Classifier: Topic :: Scientific/Engineering :: Bio-Informatics
Classifier: Topic :: Scientific/Engineering :: Image Processing
Classifier: Topic :: Scientific/Engineering :: Physics
Classifier: Topic :: Scientific/Engineering :: Visualization
Classifier: Topic :: Software Development :: Libraries
Classifier: Topic :: Software Development :: Libraries :: Python Modules
Classifier: Typing :: Typed
Provides-Extra: hub
Provides-Extra: pytorch
Provides-Extra: text
Requires-Dist: PyYAML
Requires-Dist: eval-type-backport
Requires-Dist: numpy (>=1.26)
Requires-Dist: pydantic (>=2.9.2)
Requires-Dist: scipy (>=1.14.1)
Requires-Dist: simsimd (>=5.9.2)
Requires-Dist: stringzilla (>=3.10.4)
Requires-Dist: typing-extensions (>=4.9.0)
Project-URL: Homepage, https://nrtk.readthedocs.io/
Project-URL: Repository, https://github.com/Kitware/nrtk-albumentations
